quick_api/__init__.py
quick_api/api.py
quick_api/cli.py
quick_api/core.py
quick_api/model_loader.py
quick_api/utils.py
ml_quick_api-0.1.1.dist-info/LICENSE
ml_quick_api-0.1.1.dist-info/METADATA
ml_quick_api-0.1.1.dist-info/WHEEL
ml_quick_api-0.1.1.dist-info/entry_points.txt
ml_quick_api-0.1.1.dist-info/top_level.txt
ml_quick_api-0.1.1.dist-info/RECORD
