Metadata-Version: 2.1
Name: ml-quick-api
Version: 0.1.1
Summary: Turn a Model into an API in One Line
Home-page: https://github.com/AbhishekNair050/quick-api
Author: Your Name
Author-email: abhishek.naiir@gmail.com
Classifier: Development Status :: 3 - Alpha
Classifier: Intended Audience :: Developers
Classifier: License :: OSI Approved :: MIT License
Classifier: Operating System :: OS Independent
Classifier: Programming Language :: Python :: 3
Classifier: Programming Language :: Python :: 3.7
Classifier: Programming Language :: Python :: 3.8
Classifier: Programming Language :: Python :: 3.9
Classifier: Programming Language :: Python :: 3.10
Classifier: Programming Language :: Python :: 3.11
Requires-Python: >=3.7
License-File: LICENSE
Requires-Dist: fastapi >=0.68.0
Requires-Dist: uvicorn >=0.15.0
Requires-Dist: pydantic >=1.8.0
Requires-Dist: numpy >=1.19.0
Requires-Dist: scikit-learn >=0.24.0
Requires-Dist: joblib >=1.0.0
Requires-Dist: tensorflow >=2.6.0 ; platform_machine != "arm64"
Requires-Dist: keras >=2.6.0 ; platform_machine != "arm64"
Requires-Dist: torch >=1.9.0 ; platform_machine != "arm64"
Provides-Extra: dev
Requires-Dist: pytest >=6.0 ; extra == 'dev'
Requires-Dist: pytest-asyncio >=0.15.0 ; extra == 'dev'
Requires-Dist: black >=21.0.0 ; extra == 'dev'
Requires-Dist: flake8 >=3.9.0 ; extra == 'dev'
Requires-Dist: mypy >=0.910 ; extra == 'dev'
